Workbook

Sheet 見積書
B2: 御 見 積 書
F4: 見積No. | G4: 2413-001
F5: 発行日 | G5: 46316
B6: 株式会社ジーユー 御中
B8: 下記のとおり御見積申し上げます。
B10: 御見積金額（税込） | C10: =内訳書!C32
B11: （税抜金額） | C11: =内訳書!C30 | D11: 消費税 | E11: =内訳書!C31
B13: 工事名称 | C13: GU ららぽーと富士見店 内装工事（C工事）
B14: 工事場所 | C14: 埼玉県富士見市山室1-1313 ららぽーと富士見 2F 2413区画
B15: 面積 | C15: 1,064.0㎡（約322坪） CH=3,750
B16: 工期 | C16: 2027年01月12日着工〜40夜（日曜休み） ※内装監理室の工程調整による
B17: 支払条件 | C17: 別途協議
B18: 見積有効期限 | C18: 発行日より30日間
E20: （貴社名）
E21: （住所・電話）
E22: 担当：
B24: 【別途工事・見積除外】
B25: ・B工事（指定業者） | C25: 空調室内機・GHPリモコン移設、一般換気の増移設、防災設備（感知器・スピーカー・誘導灯・SP）増移設、排煙SW移設、カットリレー本体・信号線、消火器・防火区画貫通処理
B26: ・指定会社工事 | C26: 電話（NTT）、売上端末（POS）、有線放送（USEN）、個別機械警備（セコム）
B27: ・支給品 | C27: 壁面・中央什器、レジバックカウンター什器、サービスCT、有孔ボードサッカー台、内照式ロゴサイン、LEDサイン、スタンド照明ST1、金庫
B28: ・什器据付 | C28: 支給品什器の組立・据付（ご要望により別途お見積り）
B29: ・施設負担金 | C29: 総合仮設負担金、開店前準備負担金、開店時販促負担金、内装監理費 など
B30: ・その他 | C30: 設計・監理費、諸官庁申請手数料、共用部の工事、夜間特別警備費、図面にない追加・変更工事、アスベスト調査・除去
B32: 【見積条件】
B33: ・数量は図面PDFのテキスト（仕上表・照明器具表・盤図・フロアマップ・建具表）から拾い出した。外周壁・間仕切の長さ、FRブース数、柱本数は図面寸法から概算しており、CAD実測で拾い直すと±10%程度変わる可能性がある。
B34: ・単価は2026年10月時点の首都圏商業施設テナント内装の市場単価（材工共・昼間施工）を基準にした概算。照明器具・分電盤はメーカー見積で差し替えること。
B35: ・施工指針書により作業は22:00〜07:00の夜間のみ（残業不可・溶接不可・搬入4t車まで）。労務の夜間割増を直接工事費の8%として計上した。
B36: ・工事区分は区分表（添付書類②）に従い、C工事のみを計上。A・B工事、指定会社工事、支給品は「別途工事」に記載し金額には含めない。
B37: ・床は既存躯体+水性ウレタン塗装の上に塩ビタイル直張り、天井（売場）はA工事PB面へAEP塗装、BOHはLGS+化粧石膏ボードの新設とした。
B38: ・工程は着工を2027年01月12日（夜）と仮定し、日曜夜を休みとする40夜で組んだ。実際の着工日は内装監理室の工程調整で確定する。

Sheet 内訳書
A1: 工事費内訳書
A2: 工事名称：GU ららぽーと富士見店（2413区画）内装C工事
A4: No | B4: 工種 | C4: 金額 | D4: 構成比 | E4: 備考
A5: Ⅰ 直接工事費
A6: 01 | B6: 仮設工事 | C6: =明細書!G15 | D6: =C6/C19
A7: 02 | B7: 解体・撤去工事 | C7: =明細書!G20 | D7: =C7/C19
A8: 03 | B8: 軽量鉄骨下地工事 | C8: =明細書!G31 | D8: =C8/C19
A9: 04 | B9: ボード工事 | C9: =明細書!G39 | D9: =C9/C19
A10: 05 | B10: 床工事 | C10: =明細書!G52 | D10: =C10/C19
A11: 06 | B11: 塗装工事 | C11: =明細書!G59 | D11: =C11/C19
A12: 07 | B12: クロス工事 | C12: =明細書!G63 | D12: =C12/C19
A13: 08 | B13: 木製建具・鋼製建具工事 | C13: =明細書!G75 | D13: =C13/C19
A14: 09 | B14: 金属工事 | C14: =明細書!G84 | D14: =C14/C19
A15: 10 | B15: 造作家具工事 | C15: =明細書!G101 | D15: =C15/C19
A16: 11 | B16: ガラス・ミラー工事 | C16: =明細書!G107 | D16: =C16/C19
A17: 12 | B17: サイン工事 | C17: =明細書!G119 | D17: =C17/C19
A18: 13 | B18: 電気設備工事 | C18: =明細書!G150 | D18: =C18/C19
B19: 直接工事費 計 | C19: =SUM(C6:C18)
A21: Ⅱ 共通費
B22: 夜間作業割増 | C22: =ROUND(C19*0.08,-3) | E22: 直接工事費×8%（22:00〜07:00作業・労務費の約25%相当）
B23: 共通仮設費 | C23: =ROUND(C19*0.03,-3) | E23: 直接工事費×3%
B24: 現場管理費 | C24: =ROUND(C19*0.08,-3) | E24: 直接工事費×8%（現場責任者 正副2名常駐・申請書類・竣工図）
B25: 一般管理費 | C25: =ROUND((C19+SUM(C22:C24))*0.07,-3) | E25: （直接工事費＋上記共通費）×7%
B26: 共通費 計 | C26: =SUM(C22:C25)
B28: 工事費 計（Ⅰ＋Ⅱ） | C28: =C19+C26
B29: 端数調整 | C29: =-MOD(C28,10000)
B30: 税抜合計 | C30: =C28+C29
B31: 消費税（10%） | C31: =ROUNDDOWN(C30*0.1,0)
B32: 税込合計 | C32: =C30+C31
B34: ㎡単価（税抜） | C34: =ROUND(C30/1064.0,0) | E34: 区画面積 1064.0㎡ で割った値
B35: 坪単価（税抜） | C35: =ROUND(C30/(1064.0/3.30579),0)

Sheet 明細書
A1: 工事費内訳明細書
A2: 工事名称：GU ららぽーと富士見店（2413区画）内装C工事
A4: No | B4: 名称 | C4: 仕様・摘要 | D4: 数量 | E4: 単位 | F4: 単価 | G4: 金額 | H4: 数量根拠・備考 | I4: 工種
A5: 01 仮設工事
A6: 1 | B6: 墨出し | C6: 床・壁・天井・器具位置 | D6: 1064 | E6: ㎡ | F6: 300 | G6: =ROUND(D6*F6,0) | H6: 区画面積 | I6: 01 仮設工事
A7: 2 | B7: 養生 | C7: 区画内・既存仕上・A/B工事設備・後方通路二次養生 | D7: 1 | E7: 式 | F7: 380000 | G7: =ROUND(D7*F7,0) | H7: 施工指針書 10-6 | I7: 01 仮設工事
A8: 3 | B8: 仮設電気・工事用照明 | C8: 漏電遮断器付仮設盤・投光器（照明の準備なし） | D8: 1 | E8: 式 | F8: 180000 | G8: =ROUND(D8*F8,0) | H8: 施工指針書 10-8 | I8: 01 仮設工事
A9: 4 | B9: 内部足場 | C9: ローリングタワー・可搬式作業台 CH3750 | D9: 1 | E9: 式 | F9: 280000 | G9: =ROUND(D9*F9,0) | I9: 01 仮設工事
A10: 5 | B10: 施工許可看板・掲示板・消火器 | C10: 自立型 t6ベニヤ、ABC10型 | D10: 1 | E10: 式 | F10: 60000 | G10: =ROUND(D10*F10,0) | H10: 施工指針書 6-9 | I10: 01 仮設工事
A11: 6 | B11: 日々清掃・片付け | C11: 毎夜 | D11: 40 | E11: 夜 | F11: 15000 | G11: =ROUND(D11*F11,0) | H11: 工程40夜 | I11: 01 仮設工事
A12: 7 | B12: 竣工クリーニング | C12: 床・建具・器具・ガラス | D12: 1064 | E12: ㎡ | F12: 550 | G12: =ROUND(D12*F12,0) | I12: 01 仮設工事
A13: 8 | B13: 資材搬入運搬費 | C13: 4t車以下・北荷捌所 22:00以降 | D13: 14 | E13: 台 | F13: 45000 | G13: =ROUND(D13*F13,0) | H13: 施工指針書 搬出入ルール | I13: 01 仮設工事
A14: 9 | B14: 産業廃棄物処分 | C14: 分別・搬出・マニフェスト | D14: 8 | E14: 台 | F14: 85000 | G14: =ROUND(D14*F14,0) | H14: 4t車換算 | I14: 01 仮設工事
B15: 仮設工事 小計 | G15: =SUM(G6:G14)
A17: 02 解体・撤去工事
A18: 1 | B18: 店頭サッシ撤去 | C18: 既存サッシ撤去・処分 | D18: 1 | E18: 式 | F18: 180000 | G18: =ROUND(D18*F18,0) | H18: 平面図 注記②（工事区分 要確認） | I18: 02 解体・撤去工事
A19: 2 | B19: 既存設備・残置物撤去 | C19: 既存店舗転用部の不要物撤去 | D19: 1 | E19: 式 | F19: 120000 | G19: =ROUND(D19*F19,0) | I19: 02 解体・撤去工事
B20: 解体・撤去工事 小計 | G20: =SUM(G18:G19)
A22: 03 軽量鉄骨下地工事
A23: 1 | B23: 壁下地 LGS65 | C23: C工事壁（店舗間仕切前出し）@303 H3750 | D23: 412.5 | E23: ㎡ | F23: 4200 | G23: =ROUND(D23*F23,0) | H23: 110.0m×3.75m | I23: 03 軽量鉄骨下地工事
A24: 2 | B24: 間仕切下地 LGS65 | C24: BOH間仕切 @303 H3750 | D24: 281.2 | E24: ㎡ | F24: 4200 | G24: =ROUND(D24*F24,0) | H24: 75.0m×3.75m | I24: 03 軽量鉄骨下地工事
A25: 3 | B25: 天井下地 LGS19型 | C25: BOH天井 @303 | D25: 173.1 | E25: ㎡ | F25: 3800 | G25: =ROUND(D25*F25,0) | H25: バックルーム5室計 | I25: 03 軽量鉄骨下地工事
A26: 4 | B26: ファサードボーダー下地 | C26: H650 LGS+ランナー、LEDサイン固定下地 FB t3 | D26: 39.5 | E26: ㎡ | F26: 7500 | G26: =ROUND(D26*F26,0) | H26: 重量計算書 PB 13.5+22.9+3.1㎡ | I26: 03 軽量鉄骨下地工事
A27: 5 | B27: 防煙垂れ壁 下地・ボード | C27: H500 不燃 両面PB | D27: 25 | E27: m | F27: 9500 | G27: =ROUND(D27*F27,0) | H27: 平面図 防煙垂れ壁H=500（A工事分除く・要確認） | I27: 03 軽量鉄骨下地工事
A28: 6 | B28: 建具開口補強 | D28: 11 | E28: 箇所 | F28: 12000 | G28: =ROUND(D28*F28,0) | H28: 建具表 | I28: 03 軽量鉄骨下地工事
A29: 7 | B29: 壁面什器取付下地 | C29: 合板t12 増し貼り H2400 | D29: 264 | E29: ㎡ | F29: 3200 | G29: =ROUND(D29*F29,0) | H29: 壁面什器範囲 | I29: 03 軽量鉄骨下地工事
A30: 8 | B30: ダウンライト開口・補強 | C30: A工事天井 開口φ150+補強（A-00h） | D30: 396 | E30: 箇所 | F30: 2500 | G30: =ROUND(D30*F30,0) | H30: BD+UD台数 | I30: 03 軽量鉄骨下地工事
B31: 軽量鉄骨下地工事 小計 | G31: =SUM(G23:G30)
A33: 04 ボード工事
A34: 1 | B34: 壁 PB12.5 張り | C34: 外周C工事壁 片面 | D34: 412.5 | E34: ㎡ | F34: 1600 | G34: =ROUND(D34*F34,0) | I34: 04 ボード工事
A35: 2 | B35: 間仕切 PB12.5 張り | C35: 両面 | D35: 562.5 | E35: ㎡ | F35: 1600 | G35: =ROUND(D35*F35,0) | I35: 04 ボード工事
A36: 3 | B36: 天井 化粧石膏ボード GB-D(桐) | C36: 吉野石膏 9.5 不燃NM-0128 | D36: 173.1 | E36: ㎡ | F36: 2300 | G36: =ROUND(D36*F36,0) | H36: 仕上表 BOH天井 | I36: 04 ボード工事
A37: 4 | B37: ファサード PB 張り | D37: 39.5 | E37: ㎡ | F37: 1700 | G37: =ROUND(D37*F37,0) | I37: 04 ボード工事
A38: 5 | B38: 天井点検口 | C38: 450角（C工事天井部） | D38: 6 | E38: 箇所 | F38: 15000 | G38: =ROUND(D38*F38,0) | I38: 04 ボード工事
B39: ボード工事 小計 | G39: =SUM(G34:G38)
A41: 05 床工事
A42: 1 | B42: 床下地調整 | C42: ケレン・パテしごき | D42: 1064 | E42: ㎡ | F42: 900 | G42: =ROUND(D42*F42,0) | H42: 既存躯体+水性ウレタン | I42: 05 床工事
A43: 2 | B43: 塩ビタイル ES3001-45(グレー) | C43: 川島セルコン 馬貼り FL+3 売場・FRブース外 | D43: 855.1 | E43: ㎡ | F43: 4800 | G43: =ROUND(D43*F43,0) | H43: 売場−SW+FRブース外 | I43: 05 床工事
A44: 3 | B44: 塩ビタイル クラシックP-41(グレー) | C44: 田島 FL+2 BOH・SW | D44: 194.7 | E44: ㎡ | F44: 3600 | G44: =ROUND(D44*F44,0) | H44: BOH5室+SW | I44: 05 床工事
A45: 4 | B45: 塩ビタイル ウッドライン WBH-603 | C45: 田島 乱貼り FRブース内 | D45: 14.4 | E45: ㎡ | F45: 5500 | G45: =ROUND(D45*F45,0) | H45: FR面積×40% | I45: 05 床工事
A46: 5 | B46: ソフト巾木 HB-89 H100 | C46: タジマ ライトグレー 売場 | D46: 120 | E46: m | F46: 1100 | G46: =ROUND(D46*F46,0) | I46: 05 床工事
A47: 6 | B47: ソフト巾木 TH75-96 H75 | C47: 東リ BOH | D47: 160 | E47: m | F47: 900 | G47: =ROUND(D47*F47,0) | I47: 05 床工事
A48: 7 | B48: 巾木 WTH300-96 H300 | C48: 東リ FR | D48: 40 | E48: m | F48: 2600 | G48: =ROUND(D48*F48,0) | I48: 05 床工事
A49: 8 | B49: 床見切り・リースライン際左官調整 | C49: 店頭断面詳細図 | D49: 20.8 | E49: m | F49: 3500 | G49: =ROUND(D49*F49,0) | I49: 05 床工事
A50: 9 | B50: ドットシール | C50: 避難導線・シャッターライン 450P φ30 リンテック | D50: 150 | E50: m | F50: 600 | G50: =ROUND(D50*F50,0) | I50: 05 床工事
A51: 10 | B51: 分電盤まわりイエローテープ | C51: 3M PM1981 | D51: 1 | E51: 式 | F51: 15000 | G51: =ROUND(D51*F51,0) | I51: 05 床工事
B52: 床工事 小計 | G52: =SUM(G42:G51)
A54: 06 塗装工事
A55: 1 | B55: 天井 AEP N-93(白)ツヤ消し | C55: 売場・FR CH3750 | D55: 891.1 | E55: ㎡ | F55: 1400 | G55: =ROUND(D55*F55,0) | H55: 売場+FR | I55: 06 塗装工事
A56: 2 | B56: 壁 AEP N-95(白)ツヤ消し | C56: 売場外周・BOH | D56: 975 | E56: ㎡ | F56: 1200 | G56: =ROUND(D56*F56,0) | I56: 06 塗装工事
A57: 3 | B57: ショーウィンドウ壁 AEP N-87 3分ツヤ | D57: 40 | E57: ㎡ | F57: 1500 | G57: =ROUND(D57*F57,0) | I57: 06 塗装工事
A58: 4 | B58: A工事避難扉 SOP N-87 | C58: 原状復旧対象 | D58: 3 | E58: 枚 | F58: 18000 | G58: =ROUND(D58*F58,0) | H58: 平面図 注記 | I58: 06 塗装工事
B59: 塗装工事 小計 | G59: =SUM(G55:G58)
A61: 07 クロス工事
A62: 1 | B62: クロス LW-4630(白) | C62: リリカラ 不燃NM-3991 FRブース・壁面上部 | D62: 150 | E62: ㎡ | F62: 1300 | G62: =ROUND(D62*F62,0) | I62: 07 クロス工事
B63: クロス工事 小計 | G63: =SUM(G62:G62)
A65: 08 木製建具・鋼製建具工事
A66: 1 | B66: WD-1A〜1D 片開き木製扉 | C66: W800(1D:W1025)×H2125 ポリ化粧合板・三方枠 金物込 | D66: 4 | E66: 枚 | F66: 165000 | G66: =ROUND(D66*F66,0) | H66: 建具表 | I66: 08 木製建具・鋼製建具工事
A67: 2 | B67: WD-3A 親親開き木製扉 | C67: W1250 倉庫 非常開装置付本締錠 DA-1E | D67: 1 | E67: 組 | F67: 260000 | G67: =ROUND(D67*F67,0) | H67: 建具表 | I67: 08 木製建具・鋼製建具工事
A68: 3 | B68: WD-4A FRブース扉 | C68: 木目 | D68: 1 | E68: 枚 | F68: 110000 | G68: =ROUND(D68*F68,0) | H68: 建具表 | I68: 08 木製建具・鋼製建具工事
A69: 4 | B69: WD-5A 金庫隠し扉 | C69: W850 ケースロック | D69: 1 | E69: 枚 | F69: 120000 | G69: =ROUND(D69*F69,0) | H69: 建具表 | I69: 08 木製建具・鋼製建具工事
A70: 5 | B70: WD-5D 金庫室扉 | C70: W665 固定有 | D70: 1 | E70: 組 | F70: 150000 | G70: =ROUND(D70*F70,0) | H70: 建具表 E-06 | I70: 08 木製建具・鋼製建具工事
A71: 6 | B71: WD-6 フレームレス扉 | C71: 隠し丁番・プッシュツマミ | D71: 1 | E71: 枚 | F71: 95000 | G71: =ROUND(D71*F71,0) | H71: 建具表 | I71: 08 木製建具・鋼製建具工事
A72: 7 | B72: SD-1A 片開きスチールドア | C72: W800 t1.6 ウレタン塗装 休憩室〜店長室 | D72: 1 | E72: 枚 | F72: 230000 | G72: =ROUND(D72*F72,0) | H72: 建具表 | I72: 08 木製建具・鋼製建具工事
A73: 8 | B73: SG-1 排煙水平ガラリ | C73: スチール t1.6 白塗装 | D73: 3 | E73: 箇所 | F73: 85000 | G73: =ROUND(D73*F73,0) | H73: 建具・ガラリ表（箇所数要確認） | I73: 08 木製建具・鋼製建具工事
A74: 9 | B74: 鍵（共通キー・マスターキー対応） | C74: 金庫室×5本・共通×5本 | D74: 1 | E74: 式 | F74: 60000 | G74: =ROUND(D74*F74,0) | H74: 建具表 注記 | I74: 08 木製建具・鋼製建具工事
B75: 木製建具・鋼製建具工事 小計 | G75: =SUM(G66:G74)
A77: 09 金属工事
A78: 1 | B78: 各見切り | C78: SUS・アルミ見切り（B-07） | D78: 120 | E78: m | F78: 1800 | G78: =ROUND(D78*F78,0) | I78: 09 金属工事
A79: 2 | B79: 自動ドアガード | C79: B-13 | D79: 1 | E79: 式 | F79: 120000 | G79: =ROUND(D79*F79,0) | I79: 09 金属工事
A80: 3 | B80: 防犯ネット取付 | C80: A-15 | D80: 1 | E80: 式 | F80: 80000 | G80: =ROUND(D80*F80,0) | I80: 09 金属工事
A81: 4 | B81: 台車ガード | C81: アルポリ t2 ストック扉 | D81: 1 | E81: 式 | F81: 40000 | G81: =ROUND(D81*F81,0) | I81: 09 金属工事
A82: 5 | B82: 金庫固定金具 | C82: C-05 | D82: 1 | E82: 式 | F82: 35000 | G82: =ROUND(D82*F82,0) | I82: 09 金属工事
A83: 6 | B83: ピクチャーレール | C83: VPテーブル上 B-09a | D83: 20 | E83: m | F83: 4500 | G83: =ROUND(D83*F83,0) | I83: 09 金属工事
B84: 金属工事 小計 | G84: =SUM(G78:G83)
A86: 10 造作家具工事
A87: 1 | B87: レジバック造作 | C87: C-03 | D87: 1 | E87: 式 | F87: 850000 | G87: =ROUND(D87*F87,0) | I87: 10 造作家具工事
A88: 2 | B88: レジバック棚板 | C88: W600/W900 C-04 | D88: 1 | E88: 式 | F88: 120000 | G88: =ROUND(D88*F88,0) | I88: 10 造作家具工事
A89: 3 | B89: 試着室（FR）造作 | C89: ブース間仕切・三方枠・カーテンレール D-01〜D-08 | D89: 10 | E89: 室 | F89: 180000 | G89: =ROUND(D89*F89,0) | H89: ブース数は仮定（要確認） | I89: 10 造作家具工事
A90: 4 | B90: FRソファー（大型） | C90: D-06 | D90: 2 | E90: 台 | F90: 120000 | G90: =ROUND(D90*F90,0) | I90: 10 造作家具工事
A91: 5 | B91: FR収納棚 | D91: 1 | E91: 式 | F91: 250000 | G91: =ROUND(D91*F91,0) | I91: 10 造作家具工事
A92: 6 | B92: FRカーテン | C92: 単品図 | D92: 10 | E92: 枚 | F92: 22000 | G92: =ROUND(D92*F92,0) | I92: 10 造作家具工事
A93: 7 | B93: 補正室棚板 | C93: F-03 | D93: 1 | E93: 式 | F93: 150000 | G93: =ROUND(D93*F93,0) | I93: 10 造作家具工事
A94: 8 | B94: ストックルーム棚 | C94: 棚2段（平面図） | D94: 1 | E94: 式 | F94: 600000 | G94: =ROUND(D94*F94,0) | H94: 什器支給品の場合は減額 | I94: 10 造作家具工事
A95: 9 | B95: 休憩室流し台まわり | C95: F-05（給排水接続は別途） | D95: 1 | E95: 式 | F95: 280000 | G95: =ROUND(D95*F95,0) | I95: 10 造作家具工事
A96: 10 | B96: 店長室収納棚 | C96: H2164 | D96: 1 | E96: 式 | F96: 180000 | G96: =ROUND(D96*F96,0) | I96: 10 造作家具工事
A97: 11 | B97: タペストリーボックス | C97: B-14 | D97: 2 | E97: 台 | F97: 90000 | G97: =ROUND(D97*F97,0) | I97: 10 造作家具工事
A98: 12 | B98: ファサードショーウィンドー造作 | C98: B-10 | D98: 1 | E98: 式 | F98: 650000 | G98: =ROUND(D98*F98,0) | I98: 10 造作家具工事
A99: 13 | B99: ファサードボンデパネル | C99: B-15 | D99: 1 | E99: 式 | F99: 450000 | G99: =ROUND(D99*F99,0) | I99: 10 造作家具工事
A100: 14 | B100: ロールスクリーン | C100: ショーウィンドウ B-11 | D100: 3 | E100: 台 | F100: 65000 | G100: =ROUND(D100*F100,0) | I100: 10 造作家具工事
B101: 造作家具工事 小計 | G101: =SUM(G87:G100)
A103: 11 ガラス・ミラー工事
A104: 1 | B104: 柱巻ミラー（独立柱） | C104: B-03a | D104: 6 | E104: 本 | F104: 280000 | G104: =ROUND(D104*F104,0) | H104: 本数は通り芯から仮定 | I104: 11 ガラス・ミラー工事
A105: 2 | B105: 柱巻ミラー（什器隣接柱） | C105: B-03b | D105: 4 | E105: 本 | F105: 160000 | G105: =ROUND(D105*F105,0) | I105: 11 ガラス・ミラー工事
A106: 3 | B106: FRミラー | C106: 各ブース | D106: 10 | E106: 枚 | F106: 28000 | G106: =ROUND(D106*F106,0) | I106: 11 ガラス・ミラー工事
B107: ガラス・ミラー工事 小計 | G107: =SUM(G104:G106)
A109: 12 サイン工事
A110: 1 | B110: ファサード内照式ロゴサイン 取付 | C110: G-10【支給品】電源接続含む | D110: 1 | E110: 式 | F110: 180000 | G110: =ROUND(D110*F110,0) | I110: 12 サイン工事
A111: 2 | B111: GUロゴアクリルサイン 製作取付 | C111: G-03 | D111: 1 | E111: 式 | F111: 120000 | G111: =ROUND(D111*F111,0) | I111: 12 サイン工事
A112: 3 | B112: ガラスサッシロゴサイン | C112: G-05 シート | D112: 1 | E112: 式 | F112: 60000 | G112: =ROUND(D112*F112,0) | I112: 12 サイン工事
...

Sheet 数量根拠
A1: 数量拾い根拠（図面より）
A3: 項目 | B3: 数量 | C3: 単位 | D3: 出典・算出
A4: 区画面積（照明器具表 記載床面積） | B4: 1064 | C4: ㎡ | D4: 照明器具表「床面積 1064.0㎡」
A5: BOH合計（試着室含む） | B5: 208.9 | C5: ㎡ | D5: フロアマップ BOH/TOTAL AREA 208.9㎡
A6: うち 試着室(FR) | B6: 36 | C6: ㎡ | D6: フロアマップ
A7: うち バックルーム5室計 | B7: 173.1 | C7: ㎡ | D7: 補正室15.8+倉庫94.4+備品庫17.9+休憩室35.5+店長室9.5
A8: 売場（レジ・SW含む） | B8: 855.1 | C8: ㎡ | D8: 1064.0−208.9
A9: うち レジエリア | B9: 66.8 | C9: ㎡ | D9: フロアマップ
A10: うち ショーウィンドウ | B10: 21.6 | C10: ㎡ | D10: フロアマップ
A11: 天井高 CH | B11: 3750 | C11: mm | D11: 各図 2413区画 CH=3750
A12: ファサード長さ | B12: 20.8 | C12: m | D12: ファサードボーダー重量計算 6.790+7.283+6.745
A13: 外周C工事壁 長さ（概算） | B13: 110 | C13: m | D13: 通り芯X17〜X21 8500×4=34m、奥行≒1064/34=31.3m→周長130.6m−ファサード20.8m（要実測）
A14: BOH間仕切 長さ（概算） | B14: 75 | C14: m | D14: 平面図より概算（要拾い直し）
A15: ダウンライト BD1〜BD6 | B15: 262 | C15: 台 | D15: 照明器具表 総数量
... A22: テナント分電盤 | B22: 2 | C22: 面 | D22: 盤図 U54836 電灯盤-1（200AT）・電灯盤-2（175AT）
A24: 参照図面
A25: ・※一式.pdf（施工図一式：仕上表・平面図・建具表・照明器具表・機械仕様書・各詳細図）
A26: ・製作図_GUららぽーと富士見店修正盤図(210108).pdf（河村電器 電灯盤-1/-2）
A27: ・【L1】LPFJ_2413号室区分表.pdf（A/B/C工事区分）
A28: ・LPFJ_RN2021【施工指針書一式】20210108.pdf（作業時間・搬入ルール）
A29: ・内装設計指針書.pdf

Sheet 施工工程表
A1: 施工工程表（C工事・夜間 22:00〜07:00）
A2: 工事名称：GU ららぽーと富士見店（2413区画） 着工 2027/01/12（夜）〜 2027/02/26 40夜 ※日付は作業開始夜の日付、日曜夜休み
D4: 1/12 | J4: 1/18 | Q4: 1/25 | X4: 2/1 | AE4: 2/8 | AL4: 2/15 | AS4: 2/22
C5: 日 | D5: 12 | E5: 13 | F5: 14 | G5: 15 | H5: 16 | I5: 17 | J5: 18 | K5: 19 | L5: 20 | M5: 21 | N5: 22 | O5: 23 | P5: 24 | Q5: 25 | R5: 26 | S5: 27 | T5: 28 | U5: 29 | V5: 30 | W5: 31 | X5: 1 | Y5: 2 | Z5: 3 | AA5: 4 | AB5: 5 | AC5: 6 | AD5: 7 | AE5: 8 | AF5: 9 | AG5: 10 | AH5: 11 | AI5: 12 | AJ5: 13 | AK5: 14 | AL5: 15 | AM5: 16 | AN5: 17 | AO5: 18 | AP5: 19 | AQ5: 20 | AR5: 21 | AS5: 22 | AT5: 23 | AU5: 24 | AV5: 25 | AW5: 26
C6: 曜 | D6: 火 | E6: 水 | F6: 木 | G6: 金 | H6: 土 | I6: 日 | J6: 月 | K6: 火 | L6: 水 | M6: 木 | N6: 金 | O6: 土 | P6: 日 | Q6: 月 | R6: 火 | S6: 水 | T6: 木 | U6: 金 | V6: 土 | W6: 日 | X6: 月 | Y6: 火 | Z6: 水 | AA6: 木 | AB6: 金 | AC6: 土 | AD6: 日 | AE6: 月 | AF6: 火 | AG6: 水 | AH6: 木 | AI6: 金 | AJ6: 土 | AK6: 日 | AL6: 月 | AM6: 火 | AN6: 水 | AO6: 木 | AP6: 金 | AQ6: 土 | AR6: 日 | AS6: 月 | AT6: 火 | AU6: 水 | AV6: 木 | AW6: 金
A7: No | B7: 工種・作業内容 | C7: 夜 | D7: 1 | E7: 2 | F7: 3 | G7: 4 | H7: 5 | I7: 休 | J7: 6 | K7: 7 | L7: 8 | M7: 9 | N7: 10 | O7: 11 | P7: 休 | Q7: 12 | R7: 13 | S7: 14 | T7: 15 | U7: 16 | V7: 17 | W7: 休 | X7: 18 | Y7: 19 | Z7: 20 | AA7: 21 | AB7: 22 | AC7: 23 | AD7: 休 | AE7: 24 | AF7: 25 | AG7: 26 | AH7: 27 | AI7: 28 | AJ7: 29 | AK7: 休 | AL7: 30 | AM7: 31 | AN7: 32 | AO7: 33 | AP7: 34 | AQ7: 35 | AR7: 休 | AS7: 36 | AT7: 37 | AU7: 38 | AV7: 39 | AW7: 40
A8: 1 | B8: A・B工事引渡し確認・墨出し・養生 | C8: 2
A9: 2 | B9: 撤去（店頭サッシ・既存残置物） | C9: 4
A10: 3 | B10: B工事：空調・防災・排煙SW 移設（指定業者） | C10: 12
A11: 4 | B11: 電気：幹線・天井内配管配線・分電盤据付 | C11: 12
A12: 5 | B12: LGS壁・間仕切下地／ファサード下地 | C12: 10
A13: 6 | B13: BOH天井下地・防煙垂れ壁 | C13: 7
A14: 7 | B14: ボード張り（壁・天井） | C14: 9
A15: 8 | B15: 建具枠取付・什器取付下地 | C15: 6
A16: 9 | B16: パテ・塗装（天井・壁 AEP） | C16: 10
A17: 10 | B17: クロス張り（FR） | C17: 5
A18: 11 | B18: 照明器具・コンセント・SW 取付 | C18: 11
A19: 12 | B19: 床下地調整・塩ビタイル・巾木 | C19: 8
... A30: 23 | B30: 引渡し・商品搬入 | C30: 1
E32: C工事（当社）
E33: B工事・指定会社
E34: GU様手配・引渡し
B35: ※ 作業は22:00入館〜07:00終了（夕礼・KY後に作業開始、残業不可）。搬入は22:00〜06:00、4t車まで、1台30分以内（北荷捌所）。
B36: ※ 溶接不可。火気使用は内装監理室の承認が必要（残火確認2時間）。
B37: ※ 着工10日前までに施工承認書類（様式1〜9）、7日前までに着工届・作業員名簿・A/B工事引渡し確認書を提出。

Sheet 全体工程表
A1: 全体工程表（見積〜引渡し・週単位）
A3: No | B3: 項目 | C3: 10/19 | D3: 10/26 | E3: 11/2 | F3: 11/9 | G3: 11/16 | H3: 11/23 | I3: 11/30 | J3: 12/7 | K3: 12/14 | L3: 12/21 | M3: 12/28 | N3: 1/4 | O3: 1/11 | P3: 1/18 | Q3: 1/25 | R3: 2/1 | S3: 2/8 | T3: 2/15 | U3: 2/22 | V3: 3/1
A4: 1 | B4: 図面受領・積算・見積提出
A5: 2 | B5: 見積調整（VE・数量精査）・契約
A6: 3 | B6: 実施設計図 内装監理室承認・製作図作成/承認
A7: 4 | B7: 照明器具・分電盤 発注〜納品（盤製作 約5週）
A8: 5 | B8: 建具・造作家具・ミラー・サイン 工場製作
A9: 6 | B9: 施工承認申請（様式1〜9：着工10日前）
A10: 7 | B10: 着工届・作業員名簿・A/B工事引渡し確認（7日前）
A11: 8 | B11: C工事 施工（40夜）
A12: 9 | B12: 内装監理室検査・消防検査
A13: 10 | B13: 引渡し・商品搬入・開店準備（GU様）
A14: 11 | B14: 竣工図・竣工写真・シックハウス書類提出（竣工後1ヶ月以内）
B16: ※ 年末年始（12/28〜1/4）は館の工事休止を想定し、着工を1/12とした。
