Workbook

Sheet 見積書
B2: 御 見 積 書
F4: 見積No. | G4: 2413-002
F5: 発行日 | G5: 46316
B6: 株式会社ジーユー 御中
B8: 下記のとおり御見積申し上げます。
B10: 御見積金額（税込） | C10: =内訳書!C24
B11: （税抜金額） | C11: =内訳書!C22 | D11: 消費税 | E11: =内訳書!C23
B13: 工事名称 | C13: GU ららぽーと富士見店 新装工事（C工事）
B14: 工事場所 | C14: 埼玉県富士見市山室1-1313 ららぽーと富士見 2F 2413区画
B15: 面積 | C15: 1,064.0㎡（約322坪） CH=3,750
B16: 工期 | C16: 2027年01月12日着工〜40夜（夜間工事）※内装監理室の工程調整による
B17: 支払条件 | C17: 完了時一括（別途協議）
B18: 見積有効期限 | C18: 発行日より3ヶ月
E20: 株式会社スペース
E21: （住所・電話）
E22: 担当：
B24: 【別途工事・見積除外】
B25: ・GU支給品 | C25: 照明器具・ランプ、床塩ビタイル材、アルミシート材、レジ・サービス・バックカウンター、壁面・中央什器、LEDサイン類、金庫、スタンド照明
B26: ・B工事・指定会社 | C26: 空調・換気・防災設備の増移設、排煙SW移設、カットリレー信号線、電話（NTT）、POS、有線（USEN）、機械警備
B27: ・その他 | C27: 施設負担金、設計・監理費、サッシ面遮光シート、店頭サッシ撤去（工事区分 要確認）、図面にない追加・変更工事
B29: 【見積条件】
B30: ・単価は2021年1月の同物件実績（売価）に物価補正係数 K=1.25 を掛けた2026年水準の概算です。
B31: ・数量は図面（照明器具表・盤図・建具表・フロアマップ）と同物件の実績数量を併用しました。根拠は拾い出し根拠資料を参照。
B32: ・作業は館ルールにより22:00〜07:00の夜間のみ（残業不可・溶接不可・搬入4t車まで）。

Sheet 内訳書
A1: 工事費内訳書
A2: GU ららぽーと富士見店（2413区画）内装C工事
A4: No | B4: 工種 | C4: 金額 | D4: 構成比
A5: 01 | B5: 仮設工事 | C5: =明細書!G22 | D5: =C5/C20
A6: 02 | B6: 軽鉄・ボード工事 | C6: =明細書!G47 | D6: =C6/C20
A7: 03 | B7: 床タイル工事 | C7: =明細書!G57 | D7: =C7/C20
A8: 04 | B8: 塗装工事 | C8: =明細書!G68 | D8: =C8/C20
A9: 05 | B9: 内装仕上げ工事 | C9: =明細書!G87 | D9: =C9/C20
A10: 06 | B10: 金物工事 | C10: =明細書!G100 | D10: =C10/C20
A11: 07 | B11: 木工造作工事 | C11: =明細書!G110 | D11: =C11/C20
A12: 08 | B12: 建具工事 | C12: =明細書!G123 | D12: =C12/C20
A13: 09 | B13: ガラス工事 | C13: =明細書!G135 | D13: =C13/C20
A14: 10 | B14: サイン工事 | C14: =明細書!G150 | D14: =C14/C20
A15: 11 | B15: 照明・電気工事 | C15: =明細書!G171 | D15: =C15/C20
A16: 12 | B16: 標準化項目（GU標準仕様） | C16: =明細書!G184 | D16: =C16/C20
A17: 13 | B17: 夜間工事費 | C17: =明細書!G189 | D17: =C17/C20
A18: 14 | B18: 付帯工事 | C18: =明細書!G195 | D18: =C18/C20
A19: 15 | B19: 諸経費 | C19: =明細書!G205 | D19: =C19/C20
B20: 小計 | C20: =SUM(C5:C19)
B21: 端数調整 | C21: =-MOD(C20,10000)
B22: 税抜合計 | C22: =C20+C21
B23: 消費税（10%） | C23: =ROUNDDOWN(C22*0.1,0)
B24: 税込合計 | C24: =C22+C23
B26: ㎡単価（税抜・1,064㎡） | C26: =ROUND(C22/1064.0,0)
B27: 坪単価（税抜） | C27: =ROUND(C22/(1064.0/3.30579),0)
B28: 参考：2021年実績（税抜） | C28: 42760000

Sheet 明細書
A1: 工事費内訳明細書
A2: GU ららぽーと富士見店（2413区画）内装C工事
A4: No | B4: 名称 | C4: 仕様・摘要 | D4: 数量 | E4: 単位 | F4: 単価 | G4: 金額 | H4: 備考
A5: 01 仮設工事
A6: 1 | B6: 墨出し | C6: 事前床レベル墨出し含む | D6: 1064 | E6: ㎡ | F6: 120 | G6: =ROUND(D6*F6,0) | H6: 照明器具表 床面積1,064㎡
A7: 2 | B7: 現場養生 | D7: 1064 | E7: ㎡ | F7: 120 | G7: =ROUND(D7*F7,0) | H7: 同上
A8: 3 | B8: 清掃片付け | C8: 日々 | D8: 1064 | E8: ㎡ | F8: 120 | G8: =ROUND(D8*F8,0) | H8: 同上
A9: 4 | B9: 場内小運搬 | D9: 1064 | E9: ㎡ | F9: 120 | G9: =ROUND(D9*F9,0) | H9: 同上
A10: 5 | B10: 引渡し清掃 | D10: 1064 | E10: ㎡ | F10: 380 | G10: =ROUND(D10*F10,0) | H10: 同上
A11: 6 | B11: 発生残材処分 | D11: 40 | E11: m3 | F11: 10500 | G11: =ROUND(D11*F11,0)
A12: 7 | B12: 搬出入路・ELV養生 | C12: 日々掛け払い 100m×2人 | D12: 12 | E12: 回 | F12: 18800 | G12: =ROUND(D12*F12,0)
A13: 8 | B13: ロール養生材 | C13: 100m巻 | D13: 12 | E13: 本 | F13: 6250 | G13: =ROUND(D13*F13,0)
A14: 9 | B14: 搬出入床コンパネ養生 | C14: 160m | D14: 1 | E14: 式 | F14: 312500 | G14: =ROUND(D14*F14,0) | H14: 施工指針書：300kg以上は9mmポリプレート＋コンパネ
A15: 10 | B15: 仮設分電盤・仮設照明・仮設資材 | C15: 漏電遮断器付 電源送り含む | D15: 1 | E15: 式 | F15: 45000 | G15: =ROUND(D15*F15,0) | H15: 施工指針書：仮設照明の準備なし
A16: 11 | B16: アップスター | D16: 2 | E16: 台 | F16: 36200 | G16: =ROUND(D16*F16,0)
A17: 12 | B17: フリーダムステージ | C17: CH3750 作業床 | D17: 10 | E17: 台 | F17: 50000 | G17: =ROUND(D17*F17,0)
A18: 13 | B18: 立馬 | D18: 5 | E18: 台 | F18: 18800 | G18: =ROUND(D18*F18,0)
A19: 14 | B19: ワークスペースライト | D19: 6 | E19: 台 | F19: 25000 | G19: =ROUND(D19*F19,0)
A20: 15 | B20: 足場運搬費 | D20: 3 | E20: 台 | F20: 56200 | G20: =ROUND(D20*F20,0)
A21: 16 | B21: 仮囲い撤去・清掃 | D21: 110 | E21: ㎡ | F21: 2000 | G21: =ROUND(D21*F21,0) | H21: ファサード20.8m×H≒5m
B22: 仮設工事 小計 | G22: =SUM(G6:G21)
A24: 02 軽鉄・ボード工事
A25: 1 | B25: 壁面 LGS下地 ST100 | C25: @303 | D25: 691 | E25: ㎡ | F25: 2500 | G25: =ROUND(D25*F25,0) | H25: 外周C工事壁（図面概算 110m×3.75m=413㎡＋FR・レジバック）
A26: 2 | B26: 壁面 LGS下地 ST65 | C26: @303 BOH間仕切 | D26: 285 | E26: ㎡ | F26: 2290 | G26: =ROUND(D26*F26,0) | H26: 図面概算 75m×3.75m=281㎡
A27: 3 | B27: 柱 LGS下地 ST100 | C27: 柱巻き | D27: 156 | E27: ㎡ | F27: 2290 | G27: =ROUND(D27*F27,0)
A28: 4 | B28: 壁面 PB12.5 張り | C28: 不燃 レジバック・FR壁面3×8 | D28: 965 | E28: ㎡ | F28: 1550 | G28: =ROUND(D28*F28,0) | H28: 実績1,238㎡−BOH化粧ボード変更分273㎡
A29: 5 | B29: 柱 PB12.5 張り | C29: 不燃 | D29: 156 | E29: ㎡ | F29: 1550 | G29: =ROUND(D29*F29,0)
A30: 6 | B30: ファサードゲート LGS下地 | D30: 66 | E30: ㎡ | F30: 3120 | G30: =ROUND(D30*F30,0) | H30: 図面 ボーダー重量計算 PB計39.5㎡＋見付
A31: 7 | B31: ファサードゲート PB張り | C31: 不燃12.5 | D31: 66 | E31: ㎡ | F31: 1880 | G31: =ROUND(D31*F31,0)
A32: 8 | B32: ファサード補強 | C32: 吊りボルト@900 | D32: 27 | E32: m | F32: 4380 | G32: =ROUND(D32*F32,0)
A33: 9 | B33: 天井点検口 売場 | C33: 450角 アルミフレーム | D33: 16 | E33: ヶ所 | F33: 5690 | G33: =ROUND(D33*F33,0)
A34: 10 | B34: 天井点検口 BOH | C34: 450角 アルミフレーム | D34: 8 | E34: ヶ所 | F34: 5690 | G34: =ROUND(D34*F34,0)
A35: 11 | B35: サイン用下地 | D35: 5 | E35: ヶ所 | F35: 4380 | G35: =ROUND(D35*F35,0)
A36: 12 | B36: 建具開口補強 | D36: 12 | E36: ヶ所 | F36: 5000 | G36: =ROUND(D36*F36,0) | H36: 建具表
A37: 13 | B37: DL開口補強 | C37: 半数として | D37: 198 | E37: ヶ所 | F37: 1250 | G37: =ROUND(D37*F37,0) | H37: 照明器具表 DL396台×1/2
A38: 14 | B38: 壁面排煙開口補強 | D38: 19 | E38: ヶ所 | F38: 6250 | G38: =ROUND(D38*F38,0)
A39: 15 | B39: 防煙垂壁下地追加 | C39: テンションタイプ | D39: 10 | E39: 箇所 | F39: 18800 | G39: =ROUND(D39*F39,0) | H39: 平面図 防煙垂れ壁H=500
A40: 16 | B40: 各所補足スタッド・FR手摺下地 | D40: 22 | E40: ヶ所 | F40: 1500 | G40: =ROUND(D40*F40,0)
A41: 17 | B41: 補正室 天井ケイカル増し張り | C41: 6mm＋コーナーフクビ | D41: 1 | E41: 式 | F41: 31200 | G41: =ROUND(D41*F41,0)
A42: 18 | B42: L型コーナー | C42: 塩ビコーナー 材工 | D42: 275 | E42: m | F42: 500 | G42: =ROUND(D42*F42,0)
A43: 19 | B43: ピクチャーレール下地補強 | D43: 1 | E43: 式 | F43: 50000 | G43: =ROUND(D43*F43,0) | H43: B-09a
A44: 20 | B44: 壁面・柱埋込スリット | C44: ASF-52 L2400＋専用下地PST-5＋取付 | D44: 8 | E44: 本 | F44: 10000 | G44: =ROUND(D44*F44,0)
A45: 21 | B45: 施工副資材・運搬搬入 | D45: 1 | E45: 式 | F45: 243800 | G45: =ROUND(D45*F45,0)
A46: 22 | B46: 廃材処理 | D46: 20 | E46: m3 | F46: 10500 | G46: =ROUND(D46*F46,0)
B47: 軽鉄・ボード工事 小計 | G47: =SUM(G25:G46)
A49: 03 床タイル工事
A50: 1 | B50: 売場 塩ビタイル施工 | C50: ES3001-45 馬貼り【材料GU支給】 | D50: 876 | E50: ㎡ | F50: 1310 | G50: =ROUND(D50*F50,0) | H50: 図面 売場855㎡＋FRブース外
A51: 2 | B51: FRブース内 Pタイル施工 | C51: WBH-603【材料GU支給】 | D51: 12 | E51: ㎡ | F51: 1620 | G51: =ROUND(D51*F51,0) | H51: FR小8＋大1＋HC1
A52: 3 | B52: BOH 塩ビタイル施工 | C52: P-41【材料GU支給】 | D52: 169 | E52: ㎡ | F52: 1310 | G52: =ROUND(D52*F52,0) | H52: 図面 BOH5室173㎡（SW含め要確認）
A53: 4 | B53: 床下地処理 | C53: アースシール程度 | D53: 1 | E53: 式 | F53: 37500 | G53: =ROUND(D53*F53,0)
A54: 5 | B54: 専用接着剤 | C54: アクリル系 | D54: 1057 | E54: ㎡ | F54: 380 | G54: =ROUND(D54*F54,0)
A55: 6 | B55: 各所床見切り | D55: 1 | E55: 式 | F55: 56200 | G55: =ROUND(D55*F55,0)
A56: 7 | B56: 運搬搬入 | D56: 1 | E56: 式 | F56: 137500 | G56: =ROUND(D56*F56,0)
B57: 床タイル工事 小計 | G57: =SUM(G50:G56)
A59: 04 塗装工事
A60: 1 | B60: 天井 AEP | C60: N-95ツヤ消し 寒冷紗パテ含む（BOH含む全面） | D60: 1065 | E60: ㎡ | F60: 2000 | G60: =ROUND(D60*F60,0) | H60: 区画面積
A61: 2 | B61: 壁面 AEP | C61: N-95 3分ツヤ 寒冷紗パテ含む | D61: 645 | E61: ㎡ | F61: 2000 | G61: =ROUND(D61*F61,0)
A62: 3 | B62: 柱面 AEP | C62: N-95 3分ツヤ | D62: 64 | E62: ㎡ | F62: 2000 | G62: =ROUND(D62*F62,0)
A63: 4 | B63: ファサードゲート AEP | C63: N-95 3分ツヤ | D63: 59 | E63: ㎡ | F63: 2000 | G63: =ROUND(D63*F63,0)
A64: 5 | B64: A工事避難扉 SOP | C64: N-87 原状復旧対象 | D64: 3 | E64: 枚 | F64: 18800 | G64: =ROUND(D64*F64,0) | H64: 平面図 注記
A65: 6 | B65: シャッターガイド SOP | D65: 3 | E65: 人工 | F65: 37500 | G65: =ROUND(D65*F65,0)
A66: 7 | B66: 塗装養生 | D66: 1065 | E66: ㎡ | F66: 60 | G66: =ROUND(D66*F66,0)
A67: 8 | B67: 雑塗装・補修・副資材・処分 | D67: 1 | E67: 式 | F67: 121200 | G67: =ROUND(D67*F67,0)
B68: 塗装工事 小計 | G68: =SUM(G60:G67)
A70: 05 内装仕上げ工事
A71: 1 | B71: 売場・FR ソフト巾木 | C71: HB-89 H100 | D71: 182 | E71: m | F71: 380 | G71: =ROUND(D71*F71,0)
A72: 2 | B72: 売場 塩ビFB | D72: 65 | E72: m | F72: 350 | G72: =ROUND(D72*F72,0)
A73: 3 | B73: FR・補正室 クロス（白） | C73: LW-4630（補正室はボード素地） | D73: 131 | E73: ㎡ | F73: 1560 | G73: =ROUND(D73*F73,0) | H73: 実績194㎡−補正室素地63㎡
A74: 4 | B74: スタッフルーム・店長室 化粧ボード（木目） | C74: 材工 | D74: 273 | E74: ㎡ | F74: 2380 | G74: =ROUND(D74*F74,0) | H74: 仕上表 GB-D
A75: 5 | B75: BOH ソフト巾木 | C75: TH75-96 H75 | D75: 145 | E75: m | F75: 380 | G75: =ROUND(D75*F75,0)
A76: 6 | B76: 倉庫・備品庫 巾木 | C76: WTH300-96 H300 | D76: 75 | E76: m | F76: 1120 | G76: =ROUND(D76*F76,0)
A77: 7 | B77: FRカーテン W1000 | C77: サンゲツ CK-125 H2100 | D77: 8 | E77: 枚 | F77: 16200 | G77: =ROUND(D77*F77,0)
A78: 8 | B78: FRカーテン W1500（大型） | C78: サンゲツ CK-125 H2100 | D78: 1 | E78: 枚 | F78: 18800 | G78: =ROUND(D78*F78,0)
A79: 9 | B79: カーテンレール・タッセル | C79: TOSO | D79: 9 | E79: ヶ所 | F79: 3500 | G79: =ROUND(D79*F79,0)
A80: 10 | B80: 避難通路ドットシール | C80: φ30 600P＋取付 | D80: 286 | E80: m | F80: 290 | G80: =ROUND(D80*F80,0)
A81: 11 | B81: 床用イエローテープ | C81: 3M PM1981 材工 | D81: 1 | E81: 式 | F81: 18800 | G81: =ROUND(D81*F81,0) | H81: 仕上表 分電盤まわり
A82: 12 | B82: ストック アルミシート貼り 壁 | C82: 材料別途 | D82: 165 | E82: ㎡ | F82: 1500 | G82: =ROUND(D82*F82,0) | H82: B-08
A83: 13 | B83: ストック アルミシート貼り 天井 | C83: 材料支給 | D83: 38 | E83: ㎡ | F83: 5500 | G83: =ROUND(D83*F83,0) | H83: 接着材・テープ含む
A84: 14 | B84: SW ロールスクリーン W2600×H4000 | C84: 手動 化粧BOX共 | D84: 6 | E84: 台 | F84: 130000 | G84: =ROUND(D84*F84,0) | H84: B-11（実績は追加工事）
A85: 15 | B85: SW ロールスクリーン W1800×H4000 | C85: 手動 化粧BOX共 | D85: 6 | E85: 台 | F85: 90000 | G85: =ROUND(D85*F85,0)
A86: 16 | B86: ロールスクリーン取付・運搬 | D86: 1 | E86: 式 | F86: 431200 | G86: =ROUND(D86*F86,0)
B87: 内装仕上げ工事 小計 | G87: =SUM(G71:G86)
A89: 06 金物工事
A90: 1 | B90: ファサードシャッター塞ぎパネル | C90: スチールメラ焼 白 | D90: 9 | E90: ㎡ | F90: 40000 | G90: =ROUND(D90*F90,0)
A91: 2 | B91: 同上 取付 | D91: 2 | E91: 人工 | F91: 37500 | G91: =ROUND(D91*F91,0)
A92: 3 | B92: 壁面コーナーガード | C92: Stメラ焼 16角 H4000 | D92: 67 | E92: 本 | F92: 13800 | G92: =ROUND(D92*F92,0)
A93: 4 | B93: 壁面ミラー用 メタカラー巾木 | C93: H150 L2700 | D93: 8 | E93: 本 | F93: 9000 | G93: =ROUND(D93*F93,0)
A94: 5 | B94: ピクチャーレール | C94: 白 L3000 | D94: 5 | E94: 本 | F94: 9000 | G94: =ROUND(D94*F94,0) | H94: B-09a
A95: 6 | B95: CAフック・ミニハンガー・ストップ・Sカン他 | D95: 1 | E95: 式 | F95: 98800 | G95: =ROUND(D95*F95,0)
A96: 7 | B96: FRミラーエッジ・靴べら・コートフック | D96: 1 | E96: 式 | F96: 45000 | G96: =ROUND(D96*F96,0)
A97: 8 | B97: タペストリーBOX（壁面埋込） | C97: W1020×H2230 取付・ケイカル下地・運搬込 | D97: 2 | E97: 箇所 | F97: 262500 | G97: =ROUND(D97*F97,0) | H97: B-14
A98: 9 | B98: 金庫固定金物 | C98: スチール サビ止め | D98: 1 | E98: 組 | F98: 11200 | G98: =ROUND(D98*F98,0) | H98: C-05
A99: 10 | B99: 搬入・運搬・副資材 | D99: 1 | E99: 式 | F99: 93800 | G99: =ROUND(D99*F99,0)
B100: 金物工事 小計 | G100: =SUM(G90:G99)
A102: 07 木工造作工事
A103: 1 | B103: レジバック下地コンパネ張り | D103: 1 | E103: 式 | F103: 62500 | G103: =ROUND(D103*F103,0) | H103: C-03（造作本体は支給什器）
A104: 2 | B104: HC用手摺 | C104: TOTO | D104: 2 | E104: 組 | F104: 27500 | G104: =ROUND(D104*F104,0)
A105: 3 | B105: POPケース用 木工下地 | D105: 21 | E105: ヶ所 | F105: 3750 | G105: =ROUND(D105*F105,0)
A106: 4 | B106: マスターキー対応 | D106: 1 | E106: 式 | F106: 37500 | G106: =ROUND(D106*F106,0) | H106: 建具表 注記
A107: 5 | B107: 補正室ミシン台上部棚板 | C107: W1200×D350 ブラケット・下地共 | D107: 3 | E107: 台 | F107: 31200 | G107: =ROUND(D107*F107,0) | H107: F-03
...
